<?xml version="1.0" encoding="utf-8"?>
<odoo>
    <data noupdate="1">

        <record id="membership_section.demo_member_1" model="res.partner">
            <field name="committee_membership_ids" eval="[
                    (5, 0),
                    (0, 0, {'committee_id': ref('membership_committee.demo_committee_1')})
                ]"
            />
        </record>

        <record id="membership_section.demo_member_2" model="res.partner">
            <field name="committee_membership_ids" eval="[
                    (5, 0),
                    (0, 0, {'committee_id': ref('membership_committee.demo_committee_4')})
                ]"
            />
        </record>

        <record id="membership_section.demo_member_3" model="res.partner">
            <field name="committee_membership_ids" eval="[
                    (5, 0),
                    (0, 0, {'committee_id': ref('membership_committee.demo_committee_2')}),
                    (0, 0, {'committee_id': ref('membership_committee.demo_committee_3')})
                ]"
            />
        </record>

    </data>
</odoo>
